{
  "basics": {
    "name": "Chris Small",
    "label": "Software Engineer",
    "baseUrl": "www.anotherchris.net/resume",
    "picture": "",
    "email": "chris.a.small@gmail.com",
    "phone": "on request",
    "website": "http://www.anotherchris.net",
    "alternativeResume": "http://www.anotherchris.net/resume/resume2.html",
    "summary": "C#, ASP.NET, MVC, WebApi, Javascript, Typescript, LESS/SASS, Scrum, Agil, SQL Server, MSMQ, Teamcity, Octopus, Powershell, Bash, TDD, Git, Hg, .NET Core, Linux, Docker, VMWare, AWS, Jekyll,  Appveyor, Open source",
    "location": {
      "address": "",
      "postalCode": "",
      "city": "",
      "countryCode": "",
      "region": "London"
    },
    "profiles": [
      {
        "network": "Stack-overflow",
        "username": "Chris S",
        "url": "https://stackoverflow.com/users/21574/chris-s"
      }
      {
        "network": "Linkedin",
        "username": "chris-small",
        "url": "https://www.linkedin.com/in/chris-small"
      },
      {
        "network": "Github",
        "username": "yetanotherchris",
        "url": "http://www.github.com/yetanotherchris"
      }
    ]
  },
  "work": [
    {
      "company": "Totaljobs Group",
      "website": "https://www.totaljobs.com",
      "summary": "Whilst at Totaljobs Group I have achieved the following:",
      "highlights": [
        "Worked in several roles in the organisation: Managing developer, Principal developer and currently Senior developer.",
        "In conjunction with the Packt work, my current specialism is .NET Core and ASP.NET Core with Docker, and automation of the build process.",
        "Current project is Docker/.NET Core based inside AWS ECS serving up to 80,000 requests per minute, including SNS/SQS event based system for managing various job-based events.",
        "As well as C# (backend) work we have are responsible for the devops work, we own the releases and monitoring and are pushing towards CD.",
        "The company is mostly AWS, and we manage all our AWS resources via Terraform, with additional Bash and Powershell for orchestration.",
        "I am one of the main contributors to the www.github.com/totaljobsgroup organisation, open sourcing parts of our code base to encourage open collaboration, most notably the Syringe project.",
        "Strong advocate for clean code and good, simple technical documentation in our Github Enterprise projects - I converted all our existing documentation to Markdown and then onto Github Enterprise and push for living (but minimal) documentation on all projects.",
        "I've worked on most of the Totaljobs tech stack over the years noteably: an email service that sends millions of emails daily, content service for site wide HTML/CSS/JS and a Salesforce based order fulfillment service."
      ],
      "positions": [
        {
          "position": "Senior Developer",
          "startDate": "2017-04-01"
        },
        {
          "position": "Principal Developer",
          "startDate": "2015-03-01",
          "endDate": "2017-02-01"
        },
        {
          "position": "Senior Managing Developer",
          "startDate": "2013-07-01",
          "endDate": "2015-03-01"
        },
        {
          "position": "Senior Developer",
          "startDate": "2012-07-01",
          "endDate": "2013-07-01"
        }
      ]
    },
    {
      "company": "RICS",
      "position": "Maintenance lead",
      "website": "http://www.rics.org",
      "summary": "",
      "positions": [
        {
          "position": "Maintenance lead",
          "startDate": "2011-01-01",
          "endDate": "2012-07-01"
        },
        {
          "position": "Mid-level developer",
          "startDate": "2008-01-01",
          "endDate": "2011-07-01"
        }
      ]
    },
    {
      "company": "Burges Salmon",
      "website": "https://www.burges-salmon.com",
      "positions": [
        {
          "position": "Mid-level developer",
          "startDate": "2004-01-01",
          "endDate": "2007-01-01"
        }
      ]
    },
    {
      "company": "Owtanet",
      "website": "http://www.owta.net",
      "positions": [
        {
          "position": "Developer",
          "startDate": "2002-01-01",
          "endDate": "2004-01-01"
        }
      ]
    }
  ],
  "volunteer": [],
  "education": [
    {
      "institution": "Open University",
      "area": "Computing",
      "studyType": "BSc",
      "startDate": "2007-01-01",
      "endDate": "2010-01-01",
      "gpa": "",
      "courses": []
    },
    {
      "institution": "UWE Bristol",
      "area": "Media and Cultural studies",
      "studyType": "BA (Hons)",
      "startDate": "1998",
      "endDate": "2001",
      "gpa": "",
      "courses": []
    }
  ],
  "awards": [
    {
      "title": "Tiger Award",
      "date": "2016-07-01",
      "awarder": "Stepstone",
      "summary": "Voted for by the department, this award recognises achievements by employees for the entire Stepstone set of companies."
    }
  ],
  "publications": [
    {
      "name": "Docker for ASP.NET Core MVC (video)",
      "publisher": "Packt",
      "releaseDate": "2018-03-18",
      "website": "https://www.packtpub.com/",
      "summary": "A video course to get you up and running with ASP.NET Core with Docker."
    },
    {
      "name": "Learn ASP.NET Core in 7 Days (video)",
      "publisher": "Packt",
      "releaseDate": "2018-09-01",
      "website": "https://www.packtpub.com/",
      "summary": "In progress"
    }
  ],
  "skills": [
    {
      "name": "C# .NET",
      "level": "Senior",
      "keywords": [
        "ASP.NET MVC/Core",
        ".NET Core and frameworks",
        "TDD: XUnit, NUnit",
        "IoC, Service buses (SNS, Rabbit)",
        "SQL Server, Redis, DynamoDB"
      ]
    },
    {
      "name": "Devops",
      "level": "Senior",
      "keywords": [
        "Docker",
        "Hashistack",
        "Powershell",
        "Bash",
        "AWS, VMWare, Google Cloud"
      ]
    },
    {
      "name": "Front end",
      "level": "Senior",
      "keywords": [
        "HTML 5",
        "VueJS, React, CSS, LESS/SASS",
        "NodeJS",
        "ECMAScript",
        "Typescript"
      ]
    },
    {
      "name": "CI",
      "level": "Senior",
      "keywords": [
        "Git",
        "Teamcity",
        "Octopus",
        "Kubernetes, AWS ECS",
        "Appveyor, Travis, Gitlab"
      ]
    }
  ],
  "languages": [],
  "interests": [],
  "references": []
}